length/__init__.py
length/constants.py
length/data_set.py
length/function.py
length/graph.py
length/initializer.py
length/layer.py
length/optimizer.py
length/data_sets/__init__.py
length/data_sets/fashion_mnist.py
length/data_sets/mnist.py
length/data_sets/mnist_like.py
length/functions/__init__.py
length/functions/accuracy.py
length/functions/add.py
length/functions/dropout.py
length/functions/mean_squared_error.py
length/functions/relu.py
length/functions/sigmoid.py
length/functions/softmax.py
length/functions/softmax_cross_entropy.py
length/functions/sum.py
length/initializers/__init__.py
length/initializers/xavier.py
length/layers/__init__.py
length/layers/fully_connected.py
length/models/__init__.py
length/models/mlp.py
length/optimizers/__init__.py
length/optimizers/adam.py
length/optimizers/sgd.py
length/tests/__init__.py
length/tests/gradient_checker.py
length/tests/test_train_main.py
length/tests/utils.py
length/tests/data_set_tests/__init__.py
length/tests/data_set_tests/test_data_download.py
length/tests/data_set_tests/test_data_sets.py
length/tests/function_tests/__init__.py
length/tests/function_tests/test_accuracy.py
length/tests/function_tests/test_add.py
length/tests/function_tests/test_dropout.py
length/tests/function_tests/test_function.py
length/tests/function_tests/test_mean_squared_error.py
length/tests/function_tests/test_relu.py
length/tests/function_tests/test_sigmoid.py
length/tests/function_tests/test_softmax.py
length/tests/function_tests/test_softmax_cross_entropy.py
length/tests/function_tests/test_sum.py
length/tests/graph_tests/__init__.py
length/tests/graph_tests/test_graph.py
length/tests/graph_tests/test_graph_backward.py
length/tests/layer_tests/__init__.py
length/tests/layer_tests/test_fully_connected.py
length/tests/layer_tests/test_layer.py
length/tests/optimizer_tests/__init__.py
length/tests/optimizer_tests/test_adam.py
length/tests/optimizer_tests/test_sgd.py
length_hpi-0.0.3.dist-info/LICENSE
length_hpi-0.0.3.dist-info/METADATA
length_hpi-0.0.3.dist-info/WHEEL
length_hpi-0.0.3.dist-info/top_level.txt
length_hpi-0.0.3.dist-info/RECORD
