Metadata-Version: 2.1
Name: length-hpi
Version: 0.0.3
Summary: A small framework for teaching students about basics of neural networks
Home-page: https://github.com/HPI-DeepLearning/length
Author: Christian Bartz, Joseph Bethe
Author-email: christian.bartz@hpi.de
License: UNKNOWN
Platform: UNKNOWN
Classifier: Programming Language :: Python :: 3
Classifier: Intended Audience :: Education
Classifier: License :: OSI Approved :: GNU General Public License v3 (GPLv3)
Classifier: Operating System :: OS Independent
Requires-Python: >=3.7
License-File: LICENSE
Requires-Dist: Pillow (==8.4.0)
Requires-Dist: numpy (==1.21.3)
Requires-Dist: pytest (==6.2.5)
